location/__init__.py
location/language_detector.py
location/location_detector.py
location/places_spain.json
location/utils.py
twitter_tools/__init__.py
twitter_tools/network_tools.py
twitter_tools/search_tools.py
twitter_tools/topic_analysis.py
twitter_tools/user_inference.py
twitter_toolkit-0.1.0.dist-info/WHEEL
twitter_toolkit-0.1.0.dist-info/METADATA
twitter_toolkit-0.1.0.dist-info/RECORD
