Metadata-Version: 2.1
Name: twitter-toolkit
Version: 0.1.0
Summary: This project contains different tools to help search and analyze in twitter.
Author: Diego Saby
Author-email: cuquiwi@hotmail.com
Requires-Python: >=3.8,<3.11
Classifier: Programming Language :: Python :: 3
Classifier: Programming Language :: Python :: 3.8
Classifier: Programming Language :: Python :: 3.9
Classifier: Programming Language :: Python :: 3.10
Requires-Dist: torch (>=1.13.1,<2.0.0)
